{
  "entries": [
    {
      "path": "/Users/kyandesutter/Developer/formalshell",
      "score": 13,
      "last_visit": "2025-01-28T17:33:07.314028Z"
    },
    {
      "path": "/Users/kyandesutter/Developer",
      "score": 8,
      "last_visit": "2025-01-28T16:38:18.64912Z"
    },
    {
      "path": "/Users/kyandesutter/dotfiles/.config/nix",
      "score": 8,
      "last_visit": "2025-02-02T09:42:28.887449Z"
    },
    {
      "path": "/Users/kyandesutter",
      "score": 7,
      "last_visit": "2025-02-02T09:53:26.105817Z"
    },
    {
      "path": "/Users/kyandesutter/.config",
      "score": 5,
      "last_visit": "2025-02-02T09:49:09.455922Z"
    },
    {
      "path": "/Users/kyandesutter/.config/formalshell",
      "score": 3,
      "last_visit": "2025-01-28T17:34:54.451389Z"
    },
    {
      "path": "/Users/kyandesutter/dotfiles",
      "score": 4,
      "last_visit": "2025-02-02T10:00:20.436151Z"
    },
    {
      "path": "/Users/kyandesutter/Developer/arrpc",
      "score": 2,
      "last_visit": "2025-01-28T14:48:57.976091Z"
    },
    {
      "path": "/Users/kyandesutter/Developer/terminal-doom",
      "score": 2,
      "last_visit": "2025-01-28T15:15:53.712693Z"
    },
    {
      "path": "/Users/kyandesutter/Downloads",
      "score": 2,
      "last_visit": "2025-01-28T16:38:45.591764Z"
    },
    {
      "path": "/Users/kyandesutter/dotfiles/.config",
      "score": 2,
      "last_visit": "2025-01-29T09:04:04.951568Z"
    },
    {
      "path": "/Users/kyandesutter/Downloads/Wallpapers",
      "score": 1,
      "last_visit": "2025-01-28T16:38:57.47047Z"
    },
    {
      "path": "/Users/kyandesutter/dotfiles/.config/nvim",
      "score": 1,
      "last_visit": "2025-01-29T09:04:07.603437Z"
    },
    {
      "path": "/Users/kyandesutter/.config/aerospace",
      "score": 1,
      "last_visit": "2025-01-29T20:28:16.248003Z"
    },
    {
      "path": "/Users/kyandesutter/.config/tmux",
      "score": 1,
      "last_visit": "2025-02-02T09:49:13.507221Z"
    }
  ]
}